calculadora_xyz/__init__.py
calculator_xyz-0.1.1.dist-info/METADATA
calculator_xyz-0.1.1.dist-info/WHEEL
calculator_xyz-0.1.1.dist-info/top_level.txt
calculator_xyz-0.1.1.dist-info/RECORD
